infoworks/__init__.py
infoworks/error.py
infoworks/core/__init__.py
infoworks/core/iw_authentication.py
infoworks/sdk/__init__.py
infoworks/sdk/admin_client.py
infoworks/sdk/base_client.py
infoworks/sdk/client.py
infoworks/sdk/domain_client.py
infoworks/sdk/generic_response.py
infoworks/sdk/jobmetrics.py
infoworks/sdk/jobs_client.py
infoworks/sdk/jobs_response.py
infoworks/sdk/local_configurations.py
infoworks/sdk/pipeline_client.py
infoworks/sdk/pipeline_group_client.py
infoworks/sdk/pipeline_response.py
infoworks/sdk/replicator_client.py
infoworks/sdk/source_client.py
infoworks/sdk/source_response.py
infoworks/sdk/url_builder.py
infoworks/sdk/utils.py
infoworks/sdk/workflow_client.py
infoworks/sdk/workflow_response.py
infoworks/sdk/cicd/__init__.py
infoworks/sdk/cicd/cicd_response.py
infoworks/sdk/cicd/download_configurations/__init__.py
infoworks/sdk/cicd/download_configurations/get_all_configs_from_domain.py
infoworks/sdk/cicd/download_configurations/get_entity_configuration_lineage.py
infoworks/sdk/cicd/download_configurations/get_pipeline_configuration.py
infoworks/sdk/cicd/download_configurations/get_source_configuration.py
infoworks/sdk/cicd/download_configurations/get_workflow_configuration.py
infoworks/sdk/cicd/download_configurations/lineage.py
infoworks/sdk/cicd/download_configurations/utils.py
infoworks/sdk/cicd/upload_configurations/__init__.py
infoworks/sdk/cicd/upload_configurations/cdata_source.py
infoworks/sdk/cicd/upload_configurations/csv_source.py
infoworks/sdk/cicd/upload_configurations/domains.py
infoworks/sdk/cicd/upload_configurations/file_source.py
infoworks/sdk/cicd/upload_configurations/generic_jdbc_source.py
infoworks/sdk/cicd/upload_configurations/local_configurations.py
infoworks/sdk/cicd/upload_configurations/misc.py
infoworks/sdk/cicd/upload_configurations/pipeline_group.py
infoworks/sdk/cicd/upload_configurations/pipelines.py
infoworks/sdk/cicd/upload_configurations/rdbms_source.py
infoworkssdk-5.1.0.dist-info/licenses/LICENSE
infoworkssdk-5.1.0.dist-info/METADATA
infoworkssdk-5.1.0.dist-info/WHEEL
infoworkssdk-5.1.0.dist-info/top_level.txt
infoworkssdk-5.1.0.dist-info/RECORD
