Metadata-Version: 2.4
Name: infoworkssdk
Version: 5.1.0
Summary: A package to work with Infoworks via SDK. This library is compatible with Infoworks v6.2.0 onwards. Code can be found in https://github.com/Infoworks/InfoworksPythonSDK branch: release/sdk-5.1
Home-page: https://github.com/Infoworks/InfoworksPythonSDK
Author: Infoworks CE Team
Author-email: customer-engineering@infoworks.io
Classifier: Programming Language :: Python :: 3
Classifier: License :: OSI Approved :: MIT License
Classifier: Operating System :: OS Independent
License-File: LICENSE
Requires-Dist: requests
Requires-Dist: bson
Requires-Dist: urllib3
Requires-Dist: pandas
Requires-Dist: networkx
Requires-Dist: pyyaml
Requires-Dist: tabulate
Requires-Dist: jwt
Dynamic: author
Dynamic: author-email
Dynamic: classifier
Dynamic: description
Dynamic: description-content-type
Dynamic: home-page
Dynamic: license-file
Dynamic: requires-dist
Dynamic: summary
